pytoolkit/__init__.py
pytoolkit/t2t.py
pytoolset/__init__.py
pytoolset/t2t.py
pytoolset-0.0.4.dist-info/METADATA
pytoolset-0.0.4.dist-info/RECORD
pytoolset-0.0.4.dist-info/WHEEL
pytoolset-0.0.4.dist-info/top_level.txt
pytoolset-0.0.4.dist-info/zip-safe
toolset/__init__.py
toolset/t2t.py
