Metadata-Version: 2.1
Name: pytoolset
Version: 0.0.4
Summary: this is a test package for packing python liberaries tutorial.
Home-page: UNKNOWN
Author: Zonas Wang
Author-email: zonas.wang@gmail.com
License: MIT
Keywords: test python package
Platform: UNKNOWN
Classifier: License :: OSI Approved :: MIT License
Classifier: Programming Language :: Python
Classifier: Intended Audience :: Developers
Classifier: Operating System :: OS Independent
